pysu/__init__.py
pysu/__main__.py
pysu/cli.py
pysu-1.0.1.dist-info/AUTHORS.rst
pysu-1.0.1.dist-info/LICENSE
pysu-1.0.1.dist-info/METADATA
pysu-1.0.1.dist-info/WHEEL
pysu-1.0.1.dist-info/entry_points.txt
pysu-1.0.1.dist-info/top_level.txt
pysu-1.0.1.dist-info/RECORD
